deepctl_cmd_plugin/__init__.py
deepctl_cmd_plugin/command.py
deepctl_cmd_plugin/models.py
deepctl_cmd_plugin-0.1.10.dist-info/METADATA
deepctl_cmd_plugin-0.1.10.dist-info/WHEEL
deepctl_cmd_plugin-0.1.10.dist-info/entry_points.txt
deepctl_cmd_plugin-0.1.10.dist-info/RECORD
