Metadata-Version: 2.4
Name: deepctl-cmd-plugin
Version: 0.1.10
Summary: Plugin management command for deepctl
Author-email: Deepgram DevRel <devrel@deepgram.com>
Requires-Python: >=3.10
Requires-Dist: deepctl-core>=0.1.10
Requires-Dist: packaging>=21.0
Requires-Dist: toml>=0.10.2
